odoo/addons/sale_document_condition/README.rst
odoo/addons/sale_document_condition/__init__.py
odoo/addons/sale_document_condition/__manifest__.py
odoo/addons/sale_document_condition/i18n/ca_ES.po
odoo/addons/sale_document_condition/i18n/es.po
odoo/addons/sale_document_condition/models/__init__.py
odoo/addons/sale_document_condition/models/sale_order.py
odoo/addons/sale_document_condition/models/sale_order_condition.py
odoo/addons/sale_document_condition/security/ir.model.access.csv
odoo/addons/sale_document_condition/security/security.xml
odoo/addons/sale_document_condition/static/description/icon.png
odoo/addons/sale_document_condition/views/sale_order.xml
odoo/addons/sale_document_condition/views/sale_order_condition.xml
odoo/addons/sale_document_condition/views/sale_order_report.xml
odoo11_addon_sale_document_condition-11.0.1.0.0.dist-info/METADATA
odoo11_addon_sale_document_condition-11.0.1.0.0.dist-info/WHEEL
odoo11_addon_sale_document_condition-11.0.1.0.0.dist-info/top_level.txt
odoo11_addon_sale_document_condition-11.0.1.0.0.dist-info/RECORD
